geostring/__init__.py
geostring/geostring.py
geostring/world_nicknames.csv
geostring/world_places.csv
geostring-1.0.9.dist-info/METADATA
geostring-1.0.9.dist-info/WHEEL
geostring-1.0.9.dist-info/top_level.txt
geostring-1.0.9.dist-info/RECORD
