Metadata-Version: 2.1
Name: geostring
Version: 1.0.9
Summary: geostring
Home-page: https://github.com/dfreelon/geostring/
Author: Deen Freelon
Author-email: dfreelon@gmail.com
License: UNKNOWN
Download-URL: https://github.com/dfreelon/geostring/
Keywords: geographic,location,places,geolocation
Platform: UNKNOWN
Requires-Dist: editdistance-s
Requires-Dist: pandas
Requires-Dist: unidecode
